gestell/__init__.py
gestell/sdk.py
gestell/types.py
gestell/collection/__init__.py
gestell/collection/addCategory.py
gestell/collection/create.py
gestell/collection/delete.py
gestell/collection/get.py
gestell/collection/list.py
gestell/collection/removeCategory.py
gestell/collection/update.py
gestell/collection/updateCategory.py
gestell/document/create.py
gestell/document/delete.py
gestell/document/export.py
gestell/document/get.py
gestell/document/list.py
gestell/document/presign.py
gestell/document/update.py
gestell/document/upload.py
gestell/job/cancel.py
gestell/job/get.py
gestell/job/list.py
gestell/job/reprocess.py
gestell/organization/__init__.py
gestell/organization/create.py
gestell/organization/delete.py
gestell/organization/get.py
gestell/organization/list.py
gestell/organization/update.py
gestell/organization/members/__init__.py
gestell/organization/members/add.py
gestell/organization/members/remove.py
gestell/query/exportFeatures.py
gestell/query/exportTable.py
gestell/query/features.py
gestell/query/prompt.py
gestell/query/search.py
gestell/query/table.py
gestell/service/__init__.py
gestell/service/base.py
gestell/service/collection.py
gestell/service/document.py
gestell/service/job.py
gestell/service/organization.py
gestell/service/query.py
gestell/test/__init__.py
gestell/test/sample.jpg
gestell/test/test_collection.py
gestell/test/test_document.py
gestell/test/test_error.py
gestell/test/test_organization.py
gestell/test/test_query.py
gestell/types/__init__.py
gestell/types/base.py
gestell/types/collection.py
gestell/types/document.py
gestell/types/job.py
gestell/types/layout.py
gestell/types/organization.py
gestell/types/query.py
gestell-1.4.1.dist-info/METADATA
gestell-1.4.1.dist-info/WHEEL
gestell-1.4.1.dist-info/licenses/LICENSE
gestell-1.4.1.dist-info/RECORD
