Metadata-Version: 2.4
Name: gestell
Version: 1.4.1
Summary: The Official Gestell Python SDK
Author-email: Chris Cates <hello@chriscates.ca>
License-File: LICENSE
Requires-Python: >=3
Requires-Dist: aiofile>=1.5.2
Requires-Dist: aiohttp>=2.3.1
Requires-Dist: pydantic>=0.1
Requires-Dist: python-dotenv>=0.18.0
